.hgignore
CHANGES.txt
LICENSE.txt
MANIFEST.in
README.txt
bootstrap.py
buildout.cfg
setup.py
js/__init__.py
js.fanstatictools.egg-info/PKG-INFO
js.fanstatictools.egg-info/SOURCES.txt
js.fanstatictools.egg-info/dependency_links.txt
js.fanstatictools.egg-info/entry_points.txt
js.fanstatictools.egg-info/namespace_packages.txt
js.fanstatictools.egg-info/not-zip-safe
js.fanstatictools.egg-info/requires.txt
js.fanstatictools.egg-info/top_level.txt
js/fanstatictools/__init__.py
js/fanstatictools/test_fanstatictools.txt
js/fanstatictools/resources/url.js