Metadata-Version: 1.0
Name: js.fanstatictools
Version: 0.1
Summary: Fanstatic related javascript tools packaged as a fanstatic library.
Home-page: UNKNOWN
Author: Daniel Havlik
Author-email: dh@gocept.com
License: BSD
Platform: UNKNOWN
